src/taskAutom/__init__.py
src/taskAutom/taskAutom.py
taskautom-8.4.3.dist-info/licenses/LICENSE
taskautom-8.4.3.dist-info/METADATA
taskautom-8.4.3.dist-info/WHEEL
taskautom-8.4.3.dist-info/entry_points.txt
taskautom-8.4.3.dist-info/top_level.txt
taskautom-8.4.3.dist-info/RECORD
