Metadata-Version: 2.4
Name: taskAutom
Version: 8.4.3
Summary: A simple task automation tool
Home-page: https://github.com/laimaretto/taskAutom
Author: Lucas Aimaretto
Author-email: laimaretto@gmail.com
License: BSD 3-clause
Classifier: Programming Language :: Python :: 3
Classifier: License :: OSI Approved :: BSD License
Classifier: Operating System :: OS Independent
Requires-Python: >=3.10
License-File: LICENSE
Requires-Dist: sshtunnel==0.4.0
Requires-Dist: netmiko==4.6.0
Requires-Dist: pandas==2.2.2
Requires-Dist: pyyaml==6.0.2
Requires-Dist: python-docx==0.8.11
Requires-Dist: numpy==1.26.4
Requires-Dist: paramiko==3.5.1
Dynamic: author
Dynamic: author-email
Dynamic: classifier
Dynamic: description
Dynamic: description-content-type
Dynamic: home-page
Dynamic: license
Dynamic: license-file
Dynamic: requires-dist
Dynamic: requires-python
Dynamic: summary
